t_flipflop_with_toggle_behaviour/t_flipflop.v
module t_flipflop(
	input clk,
	input reset,
	input t,
	output reg q
);

always@(posedge clk or posedge reset) begin
	if (reset)
		q <= 0;
	else if (t)
		q <= ~q;
	else
		q <= q;

end

endmodule

t_flipflop_with_toggle_behaviour/t_flipflop_tb.v
module t_flipflop_tb;

reg clk;
reg reset;
reg t;
wire q;

t_flipflop uut(
	.clk(clk),
	.reset(reset),
	.t(t),
	.q(q)
);

initial begin
	clk = 0;
	forever #5 clk=~clk;
end

initial begin
	$dumpfile("t_flipflop.vcd");
	$dumpvars(0, t_flipflop_tb);
	
	reset = 1;t = 0;
	#10 reset = 0;

	#10 t = 1;
	#10 t = 0;
	#10 t = 1;
	#10 t = 0;

	#30 $finish;
end

endmodule

t_flipflop_with_toggle_behaviour/t_flipflop.vcd
$date
	Fri May 16 17:43:58 2025
$end
$version
	Icarus Verilog
$end
$timescale
	1s
$end
$scope module t_flipflop_tb $end
$var wire 1 ! q $end
$var reg 1 " clk $end
$var reg 1 # reset $end
$var reg 1 $ t $end
$scope module uut $end
$var wire 1 " clk $end
$var wire 1 # reset $end
$var wire 1 $ t $end
$var reg 1 ! q $end
$upscope $end
$upscope $end
$enddefinitions $end
$comment Show the parameter values. $end
$dumpall
$end
#0
$dumpvars
0$
1#
0"
0!
$end
#5
1"
#10
0"
0#
#15
1"
#20
0"
1$
#25
1!
1"
#30
0"
0$
#35
1"
#40
0"
1$
#45
0!
1"
#50
0"
0$
