dff_async_reset/dff_async_reset.v
module dff_async_reset (
    input clk,
    input reset,   // asynchronous reset
    input d,
    output reg q
);

always @(posedge clk or posedge reset) begin
    if (reset)
        q <= 1'b0;     // Reset output to 0 immediately
    else
        q <= d;        // Otherwise, capture input on rising edge
end

endmodule

dff_async_reset/dff_async_reset_tb.v
module dff_async_reset_tb;

reg clk;
reg reset;
reg d;
wire q;

dff_async_reset uut (
    .clk(clk),
    .reset(reset),
    .d(d),
    .q(q)
);

initial begin
    $dumpfile("dff_async_reset.vcd");
    $dumpvars(0, dff_async_reset_tb);

    clk = 0;
    reset = 0;
    d = 0;

    #5 reset = 1;     // Apply reset
    #5 reset = 0;     // Release reset

    #10 d = 1;
    #10 d = 0;
    #10 d = 1;

    #30 $finish;
end

always #5 clk = ~clk; // Clock toggles every 5 time units

endmodule

dff_async_reset/dff_async_reset.vcd
$date
	Thu May 15 21:25:04 2025
$end
$version
	Icarus Verilog
$end
$timescale
	1s
$end
$scope module dff_async_reset_tb $end
$var wire 1 ! q $end
$var reg 1 " clk $end
$var reg 1 # d $end
$var reg 1 $ reset $end
$scope module uut $end
$var wire 1 " clk $end
$var wire 1 # d $end
$var wire 1 $ reset $end
$var reg 1 ! q $end
$upscope $end
$upscope $end
$enddefinitions $end
$comment Show the parameter values. $end
$dumpall
$end
#0
$dumpvars
0$
0#
0"
x!
$end
#5
0!
1"
1$
#10
0"
0$
#15
1"
#20
0"
1#
#25
1!
1"
#30
0"
0#
#35
0!
1"
#40
0"
1#
#45
1!
1"
